Metadata-Version: 2.2
Name: wxy_test
Version: 0.8.1
Summary: A high-throughput and memory-efficient inference and serving engine for LLMs
Home-page: https://github.com/vllm-project/vllm
Author: vLLM Team
License: Apache 2.0
Project-URL: Homepage, https://github.com/vllm-project/vllm
Project-URL: Documentation, https://vllm.readthedocs.io/en/latest/
Classifier: Programming Language :: Python :: 3.9
Classifier: Programming Language :: Python :: 3.10
Classifier: Programming Language :: Python :: 3.11
Classifier: Programming Language :: Python :: 3.12
Classifier: License :: OSI Approved :: Apache Software License
Classifier: Intended Audience :: Developers
Classifier: Intended Audience :: Information Technology
Classifier: Intended Audience :: Science/Research
Classifier: Topic :: Scientific/Engineering :: Artificial Intelligence
Classifier: Topic :: Scientific/Engineering :: Information Analysis
Requires-Python: >=3.9
License-File: LICENSE
Requires-Dist: psutil
Requires-Dist: sentencepiece
Requires-Dist: numpy<2.0.0
Requires-Dist: requests>=2.26.0
Requires-Dist: tqdm
Requires-Dist: blake3
Requires-Dist: py-cpuinfo
Requires-Dist: transformers>=4.48.2
Requires-Dist: tokenizers>=0.19.1
Requires-Dist: protobuf
Requires-Dist: fastapi<0.113.0,>=0.107.0; python_version < "3.9"
Requires-Dist: fastapi!=0.113.*,!=0.114.0,>=0.107.0; python_version >= "3.9"
Requires-Dist: aiohttp
Requires-Dist: openai>=1.52.0
Requires-Dist: uvicorn[standard]
Requires-Dist: pydantic>=2.9
Requires-Dist: prometheus_client>=0.18.0
Requires-Dist: pillow
Requires-Dist: prometheus-fastapi-instrumentator>=7.0.0
Requires-Dist: tiktoken>=0.6.0
Requires-Dist: lm-format-enforcer<0.11,>=0.10.9
Requires-Dist: outlines==0.1.11
Requires-Dist: lark==1.2.2
Requires-Dist: xgrammar>=0.1.6; platform_machine == "x86_64"
Requires-Dist: typing_extensions>=4.10
Requires-Dist: filelock>=3.16.1
Requires-Dist: partial-json-parser
Requires-Dist: pyzmq
Requires-Dist: msgspec
Requires-Dist: gguf==0.10.0
Requires-Dist: importlib_metadata
Requires-Dist: mistral_common[opencv]>=1.5.0
Requires-Dist: pyyaml
Requires-Dist: six>=1.16.0; python_version > "3.11"
Requires-Dist: setuptools>=74.1.1; python_version > "3.11"
Requires-Dist: einops
Requires-Dist: compressed-tensors==0.9.1
Requires-Dist: depyf==0.18.0
Requires-Dist: cloudpickle
Requires-Dist: torch==2.5.1+cpu; platform_machine != "ppc64le" and platform_machine != "aarch64" and platform_system != "Darwin"
Requires-Dist: torch==2.5.1; platform_machine == "ppc64le" or platform_machine == "aarch64" or platform_system == "Darwin"
Requires-Dist: torchaudio; platform_machine != "ppc64le"
Requires-Dist: torchaudio==2.5.1; platform_machine == "ppc64le"
Requires-Dist: torchvision; platform_machine != "ppc64le"
Requires-Dist: torchvision==0.20.1; platform_machine == "ppc64le"
Requires-Dist: datasets
Provides-Extra: tensorizer
Requires-Dist: tensorizer>=2.9.0; extra == "tensorizer"
Provides-Extra: runai
Requires-Dist: runai-model-streamer; extra == "runai"
Requires-Dist: runai-model-streamer-s3; extra == "runai"
Requires-Dist: boto3; extra == "runai"
Provides-Extra: audio
Requires-Dist: librosa; extra == "audio"
Requires-Dist: soundfile; extra == "audio"
Provides-Extra: video
Requires-Dist: decord; extra == "video"
Dynamic: author
Dynamic: classifier
Dynamic: description
Dynamic: description-content-type
Dynamic: home-page
Dynamic: license
Dynamic: project-url
Dynamic: provides-extra
Dynamic: requires-dist
Dynamic: requires-python
Dynamic: summary
